setup.py
shades_package/__init__.py
shades_package/shade.py
shades_package.egg-info/PKG-INFO
shades_package.egg-info/SOURCES.txt
shades_package.egg-info/dependency_links.txt
shades_package.egg-info/not-zip-safe
shades_package.egg-info/top_level.txt