Metadata-Version: 1.0
Name: shades-package
Version: 0.8
Summary: Shade just testing stuff
Home-page: UNKNOWN
Author: shadeyg56
Author-email: shadeyg56@gmail.com
License: UNKNOWN
Platform: UNKNOWN
